django_cas/__init__.py
django_cas/backends.py
django_cas/middleware.py
django_cas/views.py
django_cas_minimal-2.3.7.dist-info/DESCRIPTION.rst
django_cas_minimal-2.3.7.dist-info/METADATA
django_cas_minimal-2.3.7.dist-info/RECORD
django_cas_minimal-2.3.7.dist-info/WHEEL
django_cas_minimal-2.3.7.dist-info/metadata.json
django_cas_minimal-2.3.7.dist-info/top_level.txt
