Metadata-Version: 2.0
Name: django-cas-minimal
Version: 2.3.7
Summary: A Django CAS library for version 1.7.4 which actually works
Home-page: https://github.com/ParthKolekar/django-cas
Author: Parth Kolekar
Author-email: parth.kolekar@students.iiit.ac.in
License: BSD
Keywords: django-cas
Platform: UNKNOWN
Classifier: Development Status :: 3 - Alpha
Classifier: Framework :: Django
Classifier: Framework :: Django :: 1.7
Classifier: Intended Audience :: Developers
Classifier: License :: OSI Approved :: BSD License
Classifier: Natural Language :: English
Classifier: Programming Language :: Python :: 2
Classifier: Programming Language :: Python :: 2.7
